pterasoftware/__init__.py
pterasoftware/aerodynamics.py
pterasoftware/convergence.py
pterasoftware/functions.py
pterasoftware/geometry.py
pterasoftware/meshing.py
pterasoftware/movement.py
pterasoftware/operating_point.py
pterasoftware/output.py
pterasoftware/panel.py
pterasoftware/problems.py
pterasoftware/steady_horseshoe_vortex_lattice_method.py
pterasoftware/steady_ring_vortex_lattice_method.py
pterasoftware/trim.py
pterasoftware/unsteady_ring_vortex_lattice_method.py
pterasoftware/airfoils/2032c.dat
pterasoftware/airfoils/__init__.py
pterasoftware/airfoils/a18.dat
pterasoftware/airfoils/a18sm.dat
pterasoftware/airfoils/a63a108c.dat
pterasoftware/airfoils/ag03.dat
pterasoftware/airfoils/ag04.dat
pterasoftware/airfoils/ag08.dat
pterasoftware/airfoils/ag09.dat
pterasoftware/airfoils/ag10.dat
pterasoftware/airfoils/ag11.dat
pterasoftware/airfoils/ag12.dat
pterasoftware/airfoils/ag13.dat
pterasoftware/airfoils/ag14.dat
pterasoftware/airfoils/ag16.dat
pterasoftware/airfoils/ag17.dat
pterasoftware/airfoils/ag18.dat
pterasoftware/airfoils/ag19.dat
pterasoftware/airfoils/ag24.dat
pterasoftware/airfoils/ag25.dat
pterasoftware/airfoils/ag26.dat
pterasoftware/airfoils/ag27.dat
pterasoftware/airfoils/ag35.dat
pterasoftware/airfoils/ag36.dat
pterasoftware/airfoils/ag37.dat
pterasoftware/airfoils/ag38.dat
pterasoftware/airfoils/ag44ct02r.dat
pterasoftware/airfoils/ag455ct02r.dat
pterasoftware/airfoils/ag45c03.dat
pterasoftware/airfoils/ag45ct02r.dat
pterasoftware/airfoils/ag46c03.dat
pterasoftware/airfoils/ag46ct02r.dat
pterasoftware/airfoils/ag47c03.dat
pterasoftware/airfoils/ag47ct02r.dat
pterasoftware/airfoils/ah21-7.dat
pterasoftware/airfoils/ah21-9.dat
pterasoftware/airfoils/ah63k127.dat
pterasoftware/airfoils/ah6407.dat
pterasoftware/airfoils/ah7476.dat
pterasoftware/airfoils/ah79100a.dat
pterasoftware/airfoils/ah79100b.dat
pterasoftware/airfoils/ah79100c.dat
pterasoftware/airfoils/ah79k132.dat
pterasoftware/airfoils/ah79k135.dat
pterasoftware/airfoils/ah79k143.dat
pterasoftware-3.2.0.dist-info/licenses/LICENSE.txt
pterasoftware-3.2.0.dist-info/METADATA
pterasoftware-3.2.0.dist-info/WHEEL
pterasoftware-3.2.0.dist-info/top_level.txt
pterasoftware-3.2.0.dist-info/RECORD
