Metadata-Version: 2.4
Name: PteraSoftware
Version: 3.2.0
Summary: This is an open-source, unsteady aerodynamics solver for analyzing flapping-wing flight.
Home-page: https://github.com/camurban/pterasoftware
Author: Cameron Urban
Author-email: camerongurban@gmail.com
License: MIT
Project-URL: Bug Tracker, https://github.com/camurban/pterasoftware/issues
Keywords: python,uav,simulation,aerospace,computational-biology,cfd,solvers,computational-fluid-dynamics,aerodynamics,aeronautics,potential-flow,vlm,aerospace-engineering,unsteady-flows,aircraft-design,unmanned-aerial-vehicle,ornithopter,ornithology,vortex-lattice-method,pyvista
Classifier: Development Status :: 5 - Production/Stable
Classifier: Intended Audience :: Science/Research
Classifier: Topic :: Scientific/Engineering :: Physics
Classifier: License :: OSI Approved :: MIT License
Classifier: Natural Language :: English
Classifier: Programming Language :: Python :: 3.13
Classifier: Operating System :: OS Independent
Requires-Python: <3.14.0,>=3.13.0
License-File: LICENSE.txt
Requires-Dist: matplotlib<4.0.0,>=3.10.6
Requires-Dist: numpy<2.3.0,>=2.2.6
Requires-Dist: pyvista<1.0.0,>=0.46.3
Requires-Dist: scipy<2.0.0,>=1.16.1
Requires-Dist: numba<1.0.0,>=0.61.2
Requires-Dist: cmocean<5.0.0,>=4.0.3
Requires-Dist: tqdm<5.0.0,>=4.67.1
Requires-Dist: webp<1.0.0,>=0.4.0
Requires-Dist: PySide6<7.0.0,>=6.9.2
Dynamic: license-file
